{
	"maps": {
		"a": [
			"  111111  ",
			"          ",
			" 51111115 ",
			"          ",
			" 51111115 ",
			"          "
		],
		"b": [
			"  111115  ",
			"     a    ",
			"  112223  ",
			"          ",
			"  111111  ",
			"          "
		],
		"c": [
			"  511122  ",
			"    b     ",
			"  311111  ",
			"          ",
			"  111122  ",
			"          "
		],
		"d": [
			" 11422211 ",
			"    vv    ",
			" 11222211 ",
			"    vv    ",
			"  122221  ",
			"          "
		],
		"e": [
			" 11111115 ",
			"  vvvvvv  ",
			" 32222223 ",
			"     c    ",
			"  111111  ",
			"          "
		],
		"f": [
			" 52233222 ",
			"   vxxv   ",
			" 31111113 ",
			"    d     ",
			" 33222233 ",
			"          "
		],
		"g": [
			" 31111113 ",
			"  vvvvvv  ",
			"  111111  ",
			"  vvvvvv  ",
			"  111111  ",
			"          "
		],
		"h": [
			"  322243 ",
			"          ",
			"   1111   ",
			"    a     ",
			"   1111   ",
			"          "
		],
		"i": [
			"  511113  ",
			"      b   ",
			"  11  11  ",
			"          ",
			"  11  11  ",
			"          "
		],
		"j": [
			"  311115  ",
			"   c      ",
			"  11  11  ",
			"          ",
			"  11  11  ",
			"          "
		],
		"k": [
			"   2222  ",
			"    vv    ",
			"  222222  ",
			"     a    ",
			" 42222224 ",
			"          "
		],
		"l": [
			"   1111   ",
			" x      x ",
			"111    111",
			"  b       ",
			" 111  111 ",
			"          "
		],
		"m": [
			"    22    ",
			"    c     ",
			"   2112   ",
			"          ",
			"  112211  ",
			"          "
		],
		"n": [
			"11      11",
			" a        ",
			"11  22  11",
			"          ",
			" 11    11 ",
			"          "
		],
		"o": [
			"11      11",
			"        b ",
			"22  11  22",
			"          ",
			" 11    11 ",
			"          "
		]
	}
}
